bxbdbt/__init__.py
bxbdbt/list_tags.py
bxbdbt/update_containerfile.py
bxbdbt/utils.py
bxbdbt-0.4.7.dist-info/LICENSE
bxbdbt-0.4.7.dist-info/METADATA
bxbdbt-0.4.7.dist-info/WHEEL
bxbdbt-0.4.7.dist-info/entry_points.txt
bxbdbt-0.4.7.dist-info/RECORD
