Metadata-Version: 2.1
Name: bxbdbt
Version: 0.4.7
Summary: A bot, to build toolbx container images
License: GPLv3
Author: Christoph Görn
Author-email: goern@b4mad.net
Requires-Python: >=3.12,<4.0
Classifier: Development Status :: 4 - Beta
Classifier: License :: OSI Approved :: GNU General Public License v3 or later (GPLv3+)
Classifier: License :: Other/Proprietary License
Classifier: Natural Language :: English
Classifier: Operating System :: OS Independent
Classifier: Programming Language :: Python :: 3
Classifier: Programming Language :: Python :: 3.12
Classifier: Programming Language :: Python :: 3.13
Requires-Dist: click (>=8.1.7,<9.0.0)
Requires-Dist: python-dotenv (>=1.0.1,<2.0.0)
Requires-Dist: requests (>=2.32.3,<3.0.0)
Requires-Dist: requests-cache (>=1.2.1,<2.0.0)
